ATARRI/RRLClassifier.py
ATARRI/__init__.py
ATARRI/lightcurve_analysis.py
ATARRI-1.1.dist-info/LICENSE
ATARRI-1.1.dist-info/METADATA
ATARRI-1.1.dist-info/WHEEL
ATARRI-1.1.dist-info/top_level.txt
ATARRI-1.1.dist-info/RECORD
